shinybroker/__init__.py
shinybroker/connection.py
shinybroker/contract_samples.py
shinybroker/contractinator.py
shinybroker/format_ibkr_inputs.py
shinybroker/functionary.py
shinybroker/ib_fetch_functions.py
shinybroker/market_data_subscriptions.py
shinybroker/modals.py
shinybroker/msgs_to_ibkr.py
shinybroker/obj_defs.py
shinybroker/sb_app.py
shinybroker/sb_server.py
shinybroker/sb_ui.py
shinybroker/utils.py
shinybroker/txt_files/txt_intro.txt
shinybroker/txt_files/txt_matching_symbols.txt
shinybroker/www/css/styles.css
shinybroker/www/js/ib_message_handler.js
shinybroker/www/js/sb_functions.js
shinybroker-0.6.47.dist-info/METADATA
shinybroker-0.6.47.dist-info/WHEEL
shinybroker-0.6.47.dist-info/licenses/LICENSE
shinybroker-0.6.47.dist-info/RECORD
