Metadata-Version: 2.4
Name: shinybroker
Version: 0.6.47
Summary: Python API for Interactive Brokers
Project-URL: url, https://github.com/JakeVestal/shinybroker
Author-email: Jake Vestal <jacob.vestal@duke.edu>
License-File: LICENSE
Classifier: Operating System :: OS Independent
Classifier: Programming Language :: Python :: 3
Requires-Python: >=3.12
Requires-Dist: faicons
Requires-Dist: jinja2
Requires-Dist: pandas
Requires-Dist: plotly
Requires-Dist: requests
Requires-Dist: rich
Requires-Dist: scipy
Requires-Dist: shiny
Requires-Dist: shinywidgets
Requires-Dist: statsmodels
Provides-Extra: dev
Requires-Dist: build; extra == 'dev'
Requires-Dist: hatch; extra == 'dev'
Requires-Dist: quarto; extra == 'dev'
Requires-Dist: quartodoc; extra == 'dev'
Requires-Dist: twine; extra == 'dev'
